Workbook

Sheet Data
A12: Year | B12: Required Capacity | D12: Year | E12: Yearly Required Capacity | G12: Year | H12: Yearly Capacity Reduction Rate | I12: Yearly Capital Expenditure per GW | J12: Yearly Greenhouse gas per GW | K12: Yearly Land Use per GW | L12: Yearly Water Use per GW
A13: 2023 | B13: =1405.989+1539.4*(A13-2023)-5.0266*(A13-2023)*(A13-2023) -> 1405.989 | D13: 2024 | E13: =B14-B13 -> 1534.3734 | G13: 2025 | H13: =$E$45*POWER((1-$E$44),(G13-2024)) -> 0.038 | I13: =$E$42*POWER((1-$E$43),(G13-2024)) -> 290700000 | J13: =$E$51*POWER((1-$E$47),(G13-2024)) -> 28849600 | K13: =$E$52*POWER((1-$E$48),(G13-2024)) -> 10668804 | L13: =$E$53*POWER((1-$E$49),(G13-2024)) -> 19418000
A14: 2024 | B14: =1405.989+1539.4*(A14-2023)-5.0266*(A14-2023)*(A14-2023) -> 2940.3624 | D14: 2025 | E14: =B15-B14 -> 1524.3202 | G14: 2026 | H14: =$E$45*POWER((1-$E$44),(G14-2024)) -> 0.0361 | I14: =$E$42*POWER((1-$E$43),(G14-2024)) -> 276165000 | J14: =$E$51*POWER((1-$E$47),(G14-2024)) -> 27407120 | K14: =$E$52*POWER((1-$E$48),(G14-2024)) -> 10135364 | L14: =$E$53*POWER((1-$E$49),(G14-2024)) -> 18447100
A15: 2025 | B15: =1405.989+1539.4*(A15-2023)-5.0266*(A15-2023)*(A15-2023) -> 4464.6826 | D15: 2026 | E15: =B16-B15 -> 1514.267 | G15: 2027 | H15: =$E$45*POWER((1-$E$44),(G15-2024)) -> 0.034295 | I15: =$E$42*POWER((1-$E$43),(G15-2024)) -> 2.6235675e+08 | J15: =$E$51*POWER((1-$E$47),(G15-2024)) -> 26036764 | K15: =$E$52*POWER((1-$E$48),(G15-2024)) -> 9628595.6 | L15: =$E$53*POWER((1-$E$49),(G15-2024)) -> 17524745
A16: 2026 | B16: =1405.989+1539.4*(A16-2023)-5.0266*(A16-2023)*(A16-2023) -> 5978.9496 | D16: 2027 | E16: =B17-B16 -> 1504.2138 | G16: 2028 | H16: =$E$45*POWER((1-$E$44),(G16-2024)) -> 0.03258025 | I16: =$E$42*POWER((1-$E$43),(G16-2024)) -> 2.4923891e+08 | J16: =$E$51*POWER((1-$E$47),(G16-2024)) -> 24734926 | K16: =$E$52*POWER((1-$E$48),(G16-2024)) -> 9147165.8 | L16: =$E$53*POWER((1-$E$49),(G16-2024)) -> 16648508
A17: 2027 | B17: =1405.989+1539.4*(A17-2023)-5.0266*(A17-2023)*(A17-2023) -> 7483.1634 | D17: 2028 | E17: =B18-B17 -> 1494.1606 | G17: 2029 | H17: =$E$45*POWER((1-$E$44),(G17-2024)) -> 0.030951237 | I17: =$E$42*POWER((1-$E$43),(G17-2024)) -> 2.3677697e+08 | J17: =$E$51*POWER((1-$E$47),(G17-2024)) -> 23498180 | K17: =$E$52*POWER((1-$E$48),(G17-2024)) -> 8689807.5 | L17: =$E$53*POWER((1-$E$49),(G17-2024)) -> 15816082
A18: 2028 | B18: =1405.989+1539.4*(A18-2023)-5.0266*(A18-2023)*(A18-2023) -> 8977.324 | D18: 2029 | E18: =B19-B18 -> 1484.1074 | G18: 2030 | H18: =$E$45*POWER((1-$E$44),(G18-2024)) -> 0.029403676 | I18: =$E$42*POWER((1-$E$43),(G18-2024)) -> 2.2493812e+08 | J18: =$E$51*POWER((1-$E$47),(G18-2024)) -> 22323271 | K18: =$E$52*POWER((1-$E$48),(G18-2024)) -> 8255317.2 | L18: =$E$53*POWER((1-$E$49),(G18-2024)) -> 15025278
A19: 2029 | B19: =1405.989+1539.4*(A19-2023)-5.0266*(A19-2023)*(A19-2023) -> 10461.431 | D19: 2030 | E19: =B20-B19 -> 1474.0542 | G19: 2031 | H19: =$E$45*POWER((1-$E$44),(G19-2024)) -> 0.027933492 | I19: =$E$42*POWER((1-$E$43),(G19-2024)) -> 2.1369121e+08 | J19: =$E$51*POWER((1-$E$47),(G19-2024)) -> 21207107 | K19: =$E$52*POWER((1-$E$48),(G19-2024)) -> 7842551.3 | L19: =$E$53*POWER((1-$E$49),(G19-2024)) -> 14274014
A20: 2030 | B20: =1405.989+1539.4*(A20-2023)-5.0266*(A20-2023)*(A20-2023) -> 11935.486 | D20: 2031 | E20: =B21-B20 -> 1464.001 | G20: 2032 | H20: =$E$45*POWER((1-$E$44),(G20-2024)) -> 0.026536817 | I20: =$E$42*POWER((1-$E$43),(G20-2024)) -> 2.0300665e+08 | J20: =$E$51*POWER((1-$E$47),(G20-2024)) -> 20146752 | K20: =$E$52*POWER((1-$E$48),(G20-2024)) -> 7450423.7 | L20: =$E$53*POWER((1-$E$49),(G20-2024)) -> 13560314
A21: 2031 | B21: =1405.989+1539.4*(A21-2023)-5.0266*(A21-2023)*(A21-2023) -> 13399.487 | D21: 2032 | E21: =B22-B21 -> 1453.9478 | G21: 2033 | H21: =$E$45*POWER((1-$E$44),(G21-2024)) -> 0.025209976 | I21: =$E$42*POWER((1-$E$43),(G21-2024)) -> 1.9285632e+08 | J21: =$E$51*POWER((1-$E$47),(G21-2024)) -> 19139414 | K21: =$E$52*POWER((1-$E$48),(G21-2024)) -> 7077902.6 | L21: =$E$53*POWER((1-$E$49),(G21-2024)) -> 12882298
A22: 2032 | B22: =1405.989+1539.4*(A22-2023)-5.0266*(A22-2023)*(A22-2023) -> 14853.434 | D22: 2033 | E22: =B23-B22 -> 1443.8946 | G22: 2034 | H22: =$E$45*POWER((1-$E$44),(G22-2024)) -> 0.023949478 | I22: =$E$42*POWER((1-$E$43),(G22-2024)) -> 1.832135e+08 | J22: =$E$51*POWER((1-$E$47),(G22-2024)) -> 18182443 | K22: =$E$52*POWER((1-$E$48),(G22-2024)) -> 6724007.4 | L22: =$E$53*POWER((1-$E$49),(G22-2024)) -> 12238183
A23: 2033 | B23: =1405.989+1539.4*(A23-2023)-5.0266*(A23-2023)*(A23-2023) -> 16297.329 | D23: 2034 | E23: =B24-B23 -> 1433.8414 | G23: 2035 | H23: =$E$45*POWER((1-$E$44),(G23-2024)) -> 0.022752004 | I23: =$E$42*POWER((1-$E$43),(G23-2024)) -> 1.7405283e+08 | J23: =$E$51*POWER((1-$E$47),(G23-2024)) -> 17273321 | K23: =$E$52*POWER((1-$E$48),(G23-2024)) -> 6387807.1 | L23: =$E$53*POWER((1-$E$49),(G23-2024)) -> 11626274
A24: 2034 | B24: =1405.989+1539.4*(A24-2023)-5.0266*(A24-2023)*(A24-2023) -> 17731.17 | D24: 2035 | E24: =B25-B24 -> 1423.7882 | G24: 2036 | H24: =$E$45*POWER((1-$E$44),(G24-2024)) -> 0.021614404 | I24: =$E$42*POWER((1-$E$43),(G24-2024)) -> 1.6535019e+08 | J24: =$E$51*POWER((1-$E$47),(G24-2024)) -> 16409655 | K24: =$E$52*POWER((1-$E$48),(G24-2024)) -> 6068416.7 | L24: =$E$53*POWER((1-$E$49),(G24-2024)) -> 11044960
... A38: 2048 | B38: =1405.989+1539.4*(A38-2023)-5.0266*(A38-2023)*(A38-2023) -> 36749.364 | D38: 2049 | E38: =B39-B38 -> 1283.0434 | G38: 2050 | H38: =$E$45*POWER((1-$E$44),(G38-2024)) -> 0.010540804 | I38: =$E$42*POWER((1-$E$43),(G38-2024)) -> 80637149 | J38: =$E$51*POWER((1-$E$47),(G38-2024)) -> 8002578.2 | K38: =$E$52*POWER((1-$E$48),(G38-2024)) -> 2959415 | L38: =$E$53*POWER((1-$E$49),(G38-2024)) -> 5386350.7
A39: 2049 | B39: =1405.989+1539.4*(A39-2023)-5.0266*(A39-2023)*(A39-2023) -> 38032.407 | D39: 2050 | E39: =B40-B39 -> 1272.9902
A40: 2050 | B40: =1405.989+1539.4*(A40-2023)-5.0266*(A40-2023)*(A40-2023) -> 39305.398
A42: Initial Capital Expenditure per GW | E42: =0.306*1000000000 -> 306000000 | H42: Greenhouse gas emissions (kgCO2/(MWh/a))
A43: Annual Capital Expenditure Reduction Rate | E43: =5/100 -> 0.05 | H43: 52
A44: Annual Solar Cell Temperature Coefficient Reduction Rate | E44: =5/100 -> 0.05
A45: Capacity Reduction Rate due to PV/T | E45: =4/100 -> 0.04 | H45: Land use (m2/(MWh/a))
H46: 19.23
A47: Annual Manufacturing-related Greenhouse Gas Emission Reduction Rate | E47: =5/100 -> 0.05
A48: Annual Land Use Reduction Rate | E48: =5/100 -> 0.05 | H48: Land use (m3/(MWh/a))
A49: Annual Dissipated Water Use Reduction Rate | E49: =5/100 -> 0.05 | H49: 35
A51: Initial Greenhouse Gas Emissions per GW | E51: =H43*1000*H52 -> 30368000 | H51: MWh/a to MW transfer coefficient
A52: Initial Land Use per GW | E52: =H46*1000*H52 -> 11230320 | H52: =584 -> 584
A53: Initial Dissipated Water Use per GW | E53: =H49*1000*H52 -> 20440000

Sheet Cost Saving
A1: Annual Cost Saving from Reduced Installed Capacity
A2: Year | B2: Yearly Required Capacity | C2: Annual Capacity Saving | D2: Annual Cost Saving | F2: Discount Ratio | G2: PVC | H2: Present Value | J2: Total Cost Saving
A3: 2025 | B3: 1524.3202 | C3: =B3*Data!H13 -> 57.924168 | D3: =C3*Data!I13 -> 1.6838556e+10 | F3: 5 | G3: =1/(POWER((1+$F$3/100),(A3-2024))) -> 0.95238095 | H3: =D3*G3 -> 1.603672e+10 | I3: =SUM($H$3:H3)/1000000000 -> 16.03672 | J3: =SUM(H3:H28)/100000000/10 -> 107.79566 | K3: Billon Dollar
A4: 2026 | B4: 1514.267 | C4: =B4*Data!H14 -> 54.665039 | D4: =C4*Data!I14 -> 1.509657e+10 | G4: =1/(POWER((1+$F$3/100),(A4-2024))) -> 0.90702948 | H4: =D4*G4 -> 1.3693034e+10 | I4: =SUM($H$3:H4)/1000000000 -> 29.729754
A5: 2027 | B5: 1504.2138 | C5: =B5*Data!H15 -> 51.587012 | D5: =C5*Data!I15 -> 1.3534201e+10 | G5: =1/(POWER((1+$F$3/100),(A5-2024))) -> 0.8638376 | H5: =D5*G5 -> 1.1691352e+10 | I5: =SUM($H$3:H5)/1000000000 -> 41.421106
A6: 2028 | B6: 1494.1606 | C6: =B6*Data!H16 -> 48.680126 | D6: =C6*Data!I16 -> 1.2132982e+10 | G6: =1/(POWER((1+$F$3/100),(A6-2024))) -> 0.82270247 | H6: =D6*G6 -> 9.981834e+09 | I6: =SUM($H$3:H6)/1000000000 -> 51.40294
A7: 2029 | B7: 1484.1074 | C7: =B7*Data!H17 -> 45.934961 | D7: =C7*Data!I17 -> 1.0876341e+10 | G7: =1/(POWER((1+$F$3/100),(A7-2024))) -> 0.78352617 | H7: =D7*G7 -> 8.5218975e+09 | I7: =SUM($H$3:H7)/1000000000 -> 59.924837
A8: 2030 | B8: 1474.0542 | C8: =B8*Data!H18 -> 43.342612 | D8: =C8*Data!I18 -> 9.7494055e+09 | G8: =1/(POWER((1+$F$3/100),(A8-2024))) -> 0.7462154 | H8: =D8*G8 -> 7.2751565e+09 | I8: =SUM($H$3:H8)/1000000000 -> 67.199994
A9: 2031 | B9: 1464.001 | C9: =B9*Data!H19 -> 40.89466 | D9: =C9*Data!I19 -> 8.7388295e+09 | G9: =1/(POWER((1+$F$3/100),(A9-2024))) -> 0.71068133 | H9: =D9*G9 -> 6.210523e+09 | I9: =SUM($H$3:H9)/1000000000 -> 73.410516
A10: 2032 | B10: 1453.9478 | C10: =B10*Data!H20 -> 38.583147 | D10: =C10*Data!I20 -> 7.8326355e+09 | G10: =1/(POWER((1+$F$3/100),(A10-2024))) -> 0.67683936 | H10: =D10*G10 -> 5.301436e+09 | I10: =SUM($H$3:H10)/1000000000 -> 78.711953
A11: 2033 | B11: 1443.8946 | C11: =B11*Data!H21 -> 36.400549 | D11: =C11*Data!I21 -> 7.0200759e+09 | G11: =1/(POWER((1+$F$3/100),(A11-2024))) -> 0.64460892 | H11: =D11*G11 -> 4.5252035e+09 | I11: =SUM($H$3:H11)/1000000000 -> 83.237156
A12: 2034 | B12: 1433.8414 | C12: =B12*Data!H22 -> 34.339752 | D12: =C12*Data!I22 -> 6.2915064e+09 | G12: =1/(POWER((1+$F$3/100),(A12-2024))) -> 0.61391325 | H12: =D12*G12 -> 3.8624391e+09 | I12: =SUM($H$3:H12)/1000000000 -> 87.099595
A13: 2035 | B13: 1423.7882 | C13: =B13*Data!H23 -> 32.394034 | D13: =C13*Data!I23 -> 5.6382733e+09 | G13: =1/(POWER((1+$F$3/100),(A13-2024))) -> 0.58467929 | H13: =D13*G13 -> 3.2965816e+09 | I13: =SUM($H$3:H13)/1000000000 -> 90.396177
A14: 2036 | B14: 1413.735 | C14: =B14*Data!H24 -> 30.557039 | D14: =C14*Data!I24 -> 5.0526121e+09 | G14: =1/(POWER((1+$F$3/100),(A14-2024))) -> 0.55683742 | H14: =D14*G14 -> 2.8134835e+09 | I14: =SUM($H$3:H14)/1000000000 -> 93.20966
A15: 2037 | B15: 1403.6818 | C15: =B15*Data!H25 -> 28.822758 | D15: =C15*Data!I25 -> 4.5275559e+09 | G15: =1/(POWER((1+$F$3/100),(A15-2024))) -> 0.53032135 | H15: =D15*G15 -> 2.4010596e+09 | I15: =SUM($H$3:H15)/1000000000 -> 95.61072
... A28: 2050 | B28: 1272.9902 | C28: =B28*Data!H38 -> 13.41834 | D28: =C28*Data!I38 -> 1.0820167e+09 | G28: =1/(POWER((1+$F$3/100),(A28-2024))) -> 0.28124073 | H28: =D28*G28 -> 3.0430716e+08 | I28: =SUM($H$3:H28)/1000000000 -> 107.79566

Sheet Emission Saving
A1: Annual Land Use Saving from Reduced Installed Capacity
A2: Year | B2: Yearly Required Capacity | C2: Annual Capacity Saving | D2: Annual Emission Saving | F2: Total Emission Saving
A3: 2025 | B3: 1524.3202 | C3: =B3*Data!H13 -> 57.924168 | D3: =C3*Data!J13 -> 1.6710891e+09 | E3: =D3/1000 -> 1671089.1 | F3: =SUM(D3:D28)/1000 -> 15179596 | G3: tCO2
A4: 2026 | B4: 1514.267 | C4: =B4*Data!H14 -> 54.665039 | D4: =C4*Data!J14 -> 1.4982113e+09 | E4: =D4/1000 -> 1498211.3
A5: 2027 | B5: 1504.2138 | C5: =B5*Data!H15 -> 51.587012 | D5: =C5*Data!J15 -> 1.3431589e+09 | E5: =D5/1000 -> 1343158.9 | F5: =D3/1000/37.79/1000000000*100 -> 0.0044220404 | G5: %
A6: 2028 | B6: 1494.1606 | C6: =B6*Data!H16 -> 48.680126 | D6: =C6*Data!J16 -> 1.2040993e+09 | E6: =D6/1000 -> 1204099.3
A7: 2029 | B7: 1484.1074 | C7: =B7*Data!H17 -> 45.934961 | D7: =C7*Data!J17 -> 1.079388e+09 | E7: =D7/1000 -> 1079388
A8: 2030 | B8: 1474.0542 | C8: =B8*Data!H18 -> 43.342612 | D8: =C8*Data!J18 -> 9.6754884e+08 | E8: =D8/1000 -> 967548.84
A9: 2031 | B9: 1464.001 | C9: =B9*Data!H19 -> 40.89466 | D9: =C9*Data!J19 -> 8.6725743e+08 | E9: =D9/1000 -> 867257.43
A10: 2032 | B10: 1453.9478 | C10: =B10*Data!H20 -> 38.583147 | D10: =C10*Data!J20 -> 7.7732508e+08 | E10: =D10/1000 -> 777325.08
A11: 2033 | B11: 1443.8946 | C11: =B11*Data!H21 -> 36.400549 | D11: =C11*Data!J21 -> 6.9668518e+08 | E11: =D11/1000 -> 696685.18
A12: 2034 | B12: 1433.8414 | C12: =B12*Data!H22 -> 34.339752 | D12: =C12*Data!J22 -> 6.243806e+08 | E12: =D12/1000 -> 624380.6
A13: 2035 | B13: 1423.7882 | C13: =B13*Data!H23 -> 32.394034 | D13: =C13*Data!J23 -> 5.5955256e+08 | E13: =D13/1000 -> 559552.56
A14: 2036 | B14: 1413.735 | C14: =B14*Data!H24 -> 30.557039 | D14: =C14*Data!J24 -> 5.0143047e+08 | E14: =D14/1000 -> 501430.47
A15: 2037 | B15: 1403.6818 | C15: =B15*Data!H25 -> 28.822758 | D15: =C15*Data!J25 -> 4.4932294e+08 | E15: =D15/1000 -> 449322.94
A16: 2038 | B16: 1393.6286 | C16: =B16*Data!H26 -> 27.185512 | D16: =C16*Data!J26 -> 4.0260965e+08 | E16: =D16/1000 -> 402609.65
A17: 2039 | B17: 1383.5754 | C17: =B17*Data!H27 -> 25.639934 | D17: =C17*Data!J27 -> 3.6073408e+08 | E17: =D17/1000 -> 360734.08
... A28: 2050 | B28: 1272.9902 | C28: =B28*Data!H38 -> 13.41834 | D28: =C28*Data!J38 -> 1.0738131e+08 | E28: =D28/1000 -> 107381.31

Sheet Land Saving
A1: Annual Land Use Saving from Reduced Installed Capacity
A2: Year | B2: Yearly Required Capacity | C2: Annual Capacity Saving | D2: Annual Land Use Saving | F2: Total Land Use Saving
A3: 2025 | B3: 1524.3202 | C3: =B3*Data!H13 -> 57.924168 | D3: =C3*Data!K13 -> 6.1798159e+08 | E3: =D3/1000000 -> 617.98159 | F3: =SUM(D3:D28)/1000000 -> 5613.5314 | G3: km2
A4: 2026 | B4: 1514.267 | C4: =B4*Data!H14 -> 54.665039 | D4: =C4*Data!K14 -> 5.5405005e+08 | E4: =D4/1000000 -> 554.05005
A5: 2027 | B5: 1504.2138 | C5: =B5*Data!H15 -> 51.587012 | D5: =C5*Data!K15 -> 4.9671048e+08 | E5: =D5/1000000 -> 496.71048 | F5: =D3/1000000/82000000*100 -> 0.00075363609 | G5: %
A6: 2028 | B6: 1494.1606 | C6: =B6*Data!H16 -> 48.680126 | D6: =C6*Data!K16 -> 4.4528518e+08 | E6: =D6/1000000 -> 445.28518
A7: 2029 | B7: 1484.1074 | C7: =B7*Data!H17 -> 45.934961 | D7: =C7*Data!K17 -> 3.9916597e+08 | E7: =D7/1000000 -> 399.16597 | F7: =F3/82000000*100 -> 0.00684577 | G7: %
A8: 2030 | B8: 1474.0542 | C8: =B8*Data!H18 -> 43.342612 | D8: =C8*Data!K18 -> 3.57807e+08 | E8: =D8/1000000 -> 357.807
A9: 2031 | B9: 1464.001 | C9: =B9*Data!H19 -> 40.89466 | D9: =C9*Data!K19 -> 3.2071847e+08 | E9: =D9/1000000 -> 320.71847
A10: 2032 | B10: 1453.9478 | C10: =B10*Data!H20 -> 38.583147 | D10: =C10*Data!K20 -> 2.8746079e+08 | E10: =D10/1000000 -> 287.46079
A11: 2033 | B11: 1443.8946 | C11: =B11*Data!H21 -> 36.400549 | D11: =C11*Data!K21 -> 2.5763954e+08 | E11: =D11/1000000 -> 257.63954
A12: 2034 | B12: 1433.8414 | C12: =B12*Data!H22 -> 34.339752 | D12: =C12*Data!K22 -> 2.3090075e+08 | E12: =D12/1000000 -> 230.90075
A13: 2035 | B13: 1423.7882 | C13: =B13*Data!H23 -> 32.394034 | D13: =C13*Data!K23 -> 2.0692684e+08 | E13: =D13/1000000 -> 206.92684
A14: 2036 | B14: 1413.735 | C14: =B14*Data!H24 -> 30.557039 | D14: =C14*Data!K24 -> 1.8543284e+08 | E14: =D14/1000000 -> 185.43284
A15: 2037 | B15: 1403.6818 | C15: =B15*Data!H25 -> 28.822758 | D15: =C15*Data!K25 -> 1.6616308e+08 | E15: =D15/1000000 -> 166.16308
A16: 2038 | B16: 1393.6286 | C16: =B16*Data!H26 -> 27.185512 | D16: =C16*Data!K26 -> 1.4888815e+08 | E16: =D16/1000000 -> 148.88815
A17: 2039 | B17: 1383.5754 | C17: =B17*Data!H27 -> 25.639934 | D17: =C17*Data!K27 -> 1.3340224e+08 | E17: =D17/1000000 -> 133.40224
A18: 2040 | B18: 1373.5222 | C18: =B18*Data!H28 -> 24.18095 | D18: =C18*Data!K28 -> 1.1952071e+08 | E18: =D18/1000000 -> 119.52071
A19: 2041 | B19: 1363.469 | C19: =B19*Data!H29 -> 22.803765 | D19: =C19*Data!K29 -> 1.0707793e+08 | E19: =D19/1000000 -> 107.07793
... A28: 2050 | B28: 1272.9902 | C28: =B28*Data!H38 -> 13.41834 | D28: =C28*Data!K38 -> 39710436 | E28: =D28/1000000 -> 39.710436

Sheet Water Saving
A1: Annual Land Use Saving from Reduced Installed Capacity
A2: Year | B2: Yearly Required Capacity | C2: Annual Capacity Saving | D2: Annual Water Saving | F2: Total Water Saving
A3: 2025 | B3: 1524.3202 | C3: =B3*Data!H13 -> 57.924168 | D3: =C3*Data!L13 -> 1.1247715e+09 | E3: =D3/1000000000 -> 1.1247715 | F3: =SUM(D3:D28)/1000000000 -> 10.217036 | G3: km3
A4: 2026 | B4: 1514.267 | C4: =B4*Data!H14 -> 54.665039 | D4: =C4*Data!L14 -> 1.0084114e+09 | E4: =D4/1000000000 -> 1.0084114
A5: 2027 | B5: 1504.2138 | C5: =B5*Data!H15 -> 51.587012 | D5: =C5*Data!L15 -> 9.0404924e+08 | E5: =D5/1000000000 -> 0.90404924 | F5: =D3/1000000000/10633450/0.313*100 -> 3.379448e-05 | G5: %
A6: 2028 | B6: 1494.1606 | C6: =B6*Data!H16 -> 48.680126 | D6: =C6*Data!L16 -> 8.1045145e+08 | E6: =D6/1000000000 -> 0.81045145
A7: 2029 | B7: 1484.1074 | C7: =B7*Data!H17 -> 45.934961 | D7: =C7*Data!L17 -> 7.2651112e+08 | E7: =D7/1000000000 -> 0.72651112 | F7: =E3/80000/100000000*1000000000*100 -> 0.014059644 | G7: %
A8: 2030 | B8: 1474.0542 | C8: =B8*Data!H18 -> 43.342612 | D8: =C8*Data!L18 -> 6.512348e+08 | E8: =D8/1000000000 -> 0.6512348
A9: 2031 | B9: 1464.001 | C9: =B9*Data!H19 -> 40.89466 | D9: =C9*Data!L19 -> 5.8373096e+08 | E9: =D9/1000000000 -> 0.58373096
A10: 2032 | B10: 1453.9478 | C10: =B10*Data!H20 -> 38.583147 | D10: =C10*Data!L20 -> 5.2319957e+08 | E10: =D10/1000000000 -> 0.52319957
A11: 2033 | B11: 1443.8946 | C11: =B11*Data!H21 -> 36.400549 | D11: =C11*Data!L21 -> 4.6892271e+08 | E11: =D11/1000000000 -> 0.46892271
A12: 2034 | B12: 1433.8414 | C12: =B12*Data!H22 -> 34.339752 | D12: =C12*Data!L22 -> 4.2025618e+08 | E12: =D12/1000000000 -> 0.42025618
A13: 2035 | B13: 1423.7882 | C13: =B13*Data!H23 -> 32.394034 | D13: =C13*Data!L23 -> 3.7662192e+08 | E13: =D13/1000000000 -> 0.37662192
A14: 2036 | B14: 1413.735 | C14: =B14*Data!H24 -> 30.557039 | D14: =C14*Data!L24 -> 3.3750128e+08 | E14: =D14/1000000000 -> 0.33750128
A15: 2037 | B15: 1403.6818 | C15: =B15*Data!H25 -> 28.822758 | D15: =C15*Data!L25 -> 3.024289e+08 | E15: =D15/1000000000 -> 0.3024289
A16: 2038 | B16: 1393.6286 | C16: =B16*Data!H26 -> 27.185512 | D16: =C16*Data!L26 -> 2.7098726e+08 | E16: =D16/1000000000 -> 0.27098726
A17: 2039 | B17: 1383.5754 | C17: =B17*Data!H27 -> 25.639934 | D17: =C17*Data!L27 -> 2.4280178e+08 | E17: =D17/1000000000 -> 0.24280178
A18: 2040 | B18: 1373.5222 | C18: =B18*Data!H28 -> 24.18095 | D18: =C18*Data!L28 -> 2.175364e+08 | E18: =D18/1000000000 -> 0.2175364
A19: 2041 | B19: 1363.469 | C19: =B19*Data!H29 -> 22.803765 | D19: =C19*Data!L29 -> 1.9488963e+08 | E19: =D19/1000000000 -> 0.19488963
... A28: 2050 | B28: 1272.9902 | C28: =B28*Data!H38 -> 13.41834 | D28: =C28*Data!L38 -> 72275885 | E28: =D28/1000000000 -> 0.072275885
